{
    "annotations": {
      "list": [
        {
          "builtIn": 1,
          "datasource": "-- Grafana --",
          "enable": true,
          "hide": true,
          "iconColor": "rgba(0, 211, 255, 1)",
          "name": "Annotations & Alerts",
          "type": "dashboard"
        }
      ]
    },
    "editable": true,
    "gnetId": null,
    "graphTooltip": 0,
    "id": 1,
    "links": [],
    "panels": [
      {
        "aliasColors": {},
        "bars": false,
        "dashLength": 10,
        "dashes": false,
        "datasource": null,
        "fieldConfig": {
          "defaults": {
            "custom": {}
          },
          "overrides": []
        },
        "fill": 1,
        "fillGradient": 0,
        "gridPos": {
          "h": 8,
          "w": 12,
          "x": 0,
          "y": 0
        },
        "hiddenSeries": false,
        "id": 4,
        "legend": {
          "avg": false,
          "current": false,
          "max": false,
          "min": false,
          "show": true,
          "total": false,
          "values": false
        },
        "lines": true,
        "linewidth": 1,
        "nullPointMode": "null",
        "options": {
          "alertThreshold": true
        },
        "percentage": false,
        "pluginVersion": "7.3.3",
        "pointradius": 2,
        "points": false,
        "renderer": "flot",
        "seriesOverrides": [],
        "spaceLength": 10,
        "stack": true,
        "steppedLine": true,
        "targets": [
          {
            "metricQuery": {
              "aliasBy": "",
              "alignmentPeriod": "cloud-monitoring-auto",
              "crossSeriesReducer": "REDUCE_SUM",
              "filters": [],
              "groupBys": [
                "resource.label.namespace_name"
              ],
              "metricKind": "GAUGE",
              "metricType": "custom.googleapis.com/nuxeo/dropwizard5_nuxeo.instance-up_counter",
              "perSeriesAligner": "ALIGN_INTERPOLATE",
              "projectName": "jx-preprod",
              "unit": "1",
              "valueType": "INT64"
            },
            "queryType": "metrics",
            "refId": "A"
          }
        ],
        "thresholds": [],
        "timeFrom": null,
        "timeRegions": [],
        "timeShift": null,
        "title": "Instances per tenant",
        "tooltip": {
          "shared": true,
          "sort": 0,
          "value_type": "individual"
        },
        "type": "graph",
        "xaxis": {
          "buckets": null,
          "mode": "time",
          "name": null,
          "show": true,
          "values": []
        },
        "yaxes": [
          {
            "format": "short",
            "label": null,
            "logBase": 1,
            "max": null,
            "min": null,
            "show": true
          },
          {
            "format": "short",
            "label": null,
            "logBase": 1,
            "max": null,
            "min": null,
            "show": true
          }
        ],
        "yaxis": {
          "align": false,
          "alignLevel": null
        }
      },
      {
        "aliasColors": {},
        "bars": false,
        "dashLength": 10,
        "dashes": false,
        "datasource": null,
        "fieldConfig": {
          "defaults": {
            "custom": {
              "align": null,
              "filterable": false
            },
            "mappings": [],
            "thresholds": {
              "mode": "absolute",
              "steps": [
                {
                  "color": "green",
                  "value": null
                },
                {
                  "color": "red",
                  "value": 80
                }
              ]
            }
          },
          "overrides": []
        },
        "fill": 0,
        "fillGradient": 0,
        "gridPos": {
          "h": 8,
          "w": 12,
          "x": 12,
          "y": 0
        },
        "hiddenSeries": false,
        "id": 7,
        "legend": {
          "avg": false,
          "current": false,
          "max": false,
          "min": false,
          "show": true,
          "total": false,
          "values": false
        },
        "lines": true,
        "linewidth": 1,
        "nullPointMode": "null",
        "options": {
          "alertThreshold": true
        },
        "percentage": false,
        "pluginVersion": "7.3.3",
        "pointradius": 2,
        "points": true,
        "renderer": "flot",
        "seriesOverrides": [],
        "spaceLength": 10,
        "stack": false,
        "steppedLine": false,
        "targets": [
          {
            "metricQuery": {
              "aliasBy": "",
              "alignmentPeriod": "cloud-monitoring-auto",
              "crossSeriesReducer": "REDUCE_SUM",
              "filters": [],
              "groupBys": [
                "resource.label.namespace_name"
              ],
              "metricKind": "GAUGE",
              "metricType": "custom.googleapis.com/nuxeo/dropwizard5_nuxeo.instance-up_counter",
              "perSeriesAligner": "ALIGN_INTERPOLATE",
              "projectName": "jx-preprod",
              "unit": "1",
              "valueType": "INT64"
            },
            "queryType": "metrics",
            "refId": "A"
          }
        ],
        "thresholds": [],
        "timeFrom": null,
        "timeRegions": [],
        "timeShift": null,
        "title": "Instances per tenant",
        "tooltip": {
          "shared": true,
          "sort": 0,
          "value_type": "individual"
        },
        "type": "graph",
        "xaxis": {
          "buckets": null,
          "mode": "time",
          "name": null,
          "show": true,
          "values": []
        },
        "yaxes": [
          {
            "format": "short",
            "label": null,
            "logBase": 1,
            "max": null,
            "min": null,
            "show": true
          },
          {
            "format": "short",
            "label": null,
            "logBase": 1,
            "max": null,
            "min": null,
            "show": true
          }
        ],
        "yaxis": {
          "align": false,
          "alignLevel": null
        }
      },
      {
        "aliasColors": {},
        "bars": false,
        "dashLength": 10,
        "dashes": false,
        "datasource": null,
        "fieldConfig": {
          "defaults": {
            "custom": {}
          },
          "overrides": []
        },
        "fill": 1,
        "fillGradient": 0,
        "gridPos": {
          "h": 9,
          "w": 12,
          "x": 0,
          "y": 8
        },
        "hiddenSeries": false,
        "id": 2,
        "legend": {
          "avg": false,
          "current": false,
          "max": false,
          "min": false,
          "show": true,
          "total": false,
          "values": false
        },
        "lines": true,
        "linewidth": 1,
        "nullPointMode": "null",
        "options": {
          "alertThreshold": true
        },
        "percentage": false,
        "pluginVersion": "7.3.3",
        "pointradius": 2,
        "points": false,
        "renderer": "flot",
        "seriesOverrides": [],
        "spaceLength": 10,
        "stack": false,
        "steppedLine": false,
        "targets": [
          {
            "metricQuery": {
              "aliasBy": "",
              "alignmentPeriod": "cloud-monitoring-auto",
              "crossSeriesReducer": "REDUCE_SUM",
              "filters": [
                "metric.label.cluster_name",
                "=",
                "multitenants"
              ],
              "groupBys": [
                "metric.label.namespace_name"
              ],
              "metricKind": "GAUGE",
              "metricType": "custom.googleapis.com/nuxeo/dropwizard5_nuxeo.works.global.queue.completed_gauge",
              "perSeriesAligner": "ALIGN_INTERPOLATE",
              "projectName": "jx-preprod",
              "unit": "1",
              "valueType": "DOUBLE"
            },
            "queryType": "metrics",
            "refId": "A"
          }
        ],
        "thresholds": [],
        "timeFrom": null,
        "timeRegions": [],
        "timeShift": null,
        "title": "Completed Works",
        "tooltip": {
          "shared": true,
          "sort": 0,
          "value_type": "individual"
        },
        "type": "graph",
        "xaxis": {
          "buckets": null,
          "mode": "time",
          "name": null,
          "show": true,
          "values": []
        },
        "yaxes": [
          {
            "format": "short",
            "label": null,
            "logBase": 1,
            "max": null,
            "min": null,
            "show": true
          },
          {
            "format": "short",
            "label": null,
            "logBase": 1,
            "max": null,
            "min": null,
            "show": true
          }
        ],
        "yaxis": {
          "align": false,
          "alignLevel": null
        }
      },
      {
        "aliasColors": {},
        "bars": false,
        "dashLength": 10,
        "dashes": false,
        "datasource": null,
        "description": "",
        "fieldConfig": {
          "defaults": {
            "custom": {}
          },
          "overrides": []
        },
        "fill": 1,
        "fillGradient": 0,
        "gridPos": {
          "h": 8,
          "w": 12,
          "x": 12,
          "y": 8
        },
        "hiddenSeries": false,
        "id": 6,
        "legend": {
          "avg": false,
          "current": false,
          "max": false,
          "min": false,
          "show": true,
          "total": false,
          "values": false
        },
        "lines": true,
        "linewidth": 1,
        "nullPointMode": "null",
        "options": {
          "alertThreshold": true
        },
        "percentage": false,
        "pluginVersion": "7.3.3",
        "pointradius": 2,
        "points": false,
        "renderer": "flot",
        "seriesOverrides": [],
        "spaceLength": 10,
        "stack": false,
        "steppedLine": false,
        "targets": [
          {
            "metricQuery": {
              "aliasBy": "",
              "alignmentPeriod": "cloud-monitoring-auto",
              "crossSeriesReducer": "REDUCE_SUM",
              "filters": [],
              "groupBys": [
                "metric.label.namespace_name"
              ],
              "metricKind": "GAUGE",
              "metricType": "custom.googleapis.com/nuxeo/dropwizard5_nuxeo.async.load_gauge",
              "perSeriesAligner": "ALIGN_INTERPOLATE",
              "projectName": "jx-preprod",
              "unit": "1",
              "valueType": "DOUBLE"
            },
            "queryType": "metrics",
            "refId": "A"
          }
        ],
        "thresholds": [],
        "timeFrom": null,
        "timeRegions": [],
        "timeShift": null,
        "title": "Async Load",
        "tooltip": {
          "shared": true,
          "sort": 0,
          "value_type": "individual"
        },
        "type": "graph",
        "xaxis": {
          "buckets": null,
          "mode": "time",
          "name": null,
          "show": true,
          "values": []
        },
        "yaxes": [
          {
            "format": "short",
            "label": null,
            "logBase": 1,
            "max": null,
            "min": null,
            "show": true
          },
          {
            "format": "short",
            "label": null,
            "logBase": 1,
            "max": null,
            "min": null,
            "show": true
          }
        ],
        "yaxis": {
          "align": false,
          "alignLevel": null
        }
      }
    ],
    "refresh": false,
    "schemaVersion": 26,
    "style": "dark",
    "tags": [],
    "templating": {
      "list": []
    },
    "time": {
      "from": "2020-12-17T23:04:56.936Z",
      "to": "2020-12-17T23:36:14.145Z"
    },
    "timepicker": {},
    "timezone": "",
    "title": "Tenants Dashboard",
    "uid": "Tj89Tl1Gk",
    "version": 6
  }